setup.py
galena/__init__.py
galena/client.py
galena/tests.py
galena.egg-info/PKG-INFO
galena.egg-info/SOURCES.txt
galena.egg-info/dependency_links.txt
galena.egg-info/not-zip-safe
galena.egg-info/top_level.txt