Metadata-Version: 1.0
Name: galena
Version: 0.3
Summary: Dumb but useful graphite/carbon client.
Home-page: https://github.com/20minutes/galena
Author: Timothée Peignier
Author-email: tpeignier@20minutes.fr
License: UNKNOWN
Platform: UNKNOWN
Classifier: Intended Audience :: System Administrators
Classifier: Intended Audience :: Developers
Classifier: License :: OSI Approved :: MIT License
Classifier: Operating System :: OS Independent
Classifier: Programming Language :: Python
Classifier: Topic :: Utilities
